<?xml version="1.0" encoding="utf-8" ?>
<dwsync>
<file name="arrow-down.png" server="piktoresk.berlin" local="131969441080733498" remote="131967945600000000" Dst="1" />
<file name="arrow-right.png" server="piktoresk.berlin" local="131969441081338592" remote="131967945600000000" Dst="1" />
<file name="close-white.png" server="piktoresk.berlin" local="131969441082636665" remote="131967945600000000" Dst="1" />
<file name="bundle-icon.png" server="piktoresk.berlin" local="131969441083176928" remote="131967945600000000" Dst="1" />
<file name="close.png" server="piktoresk.berlin" local="131969441083532622" remote="131967945600000000" Dst="1" />
<file name="loading.gif" server="piktoresk.berlin" local="131969441084468684" remote="131967945600000000" Dst="1" />
<file name="menu-icon.svg" server="piktoresk.berlin" local="131969441084851731" remote="131967945600000000" Dst="1" />
<file name="order-asc.png" server="piktoresk.berlin" local="131969441085437277" remote="131967945600000000" Dst="1" />
<file name="order-desc.png" server="piktoresk.berlin" local="131969441086365778" remote="131967945600000000" Dst="1" />
<file name="ordering-icons.png" server="piktoresk.berlin" local="131969441086733825" remote="131967945600000000" Dst="1" />
<file name="thumbnail-placeholder.png" server="piktoresk.berlin" local="131969441087940283" remote="131967945600000000" Dst="1" />
<file name="wpspin_light-2x.gif" server="piktoresk.berlin" local="131969441390694542" remote="131967945600000000" Dst="1" />
<file name="wpspin_light.gif" server="piktoresk.berlin" local="131969441390687046" remote="131967945600000000" Dst="1" />
</dwsync>